<step title="Incoming Request" date="2025-12-04T15:34:59.847" instance="33847b" url="/api/publish?async=true&amp;deployer=GITHUB_ONE_DEPLOY&amp;type=zip&amp;message=%7B%22type%22%3A%22deployment%22%2C%22sha%22%3A%22a452320e1d11ff70c5028d060cfb0ceaf2da885c%22%2C%22repoName%22%3A%22newthingsit%2Faudit_Checklists-app%22%2C%22actor%22%3A%22newthingsit%22%2C%22slotName%22%3A%22production%22%2C%22commitMessage%22%3A%22release%3A%20v2.0.0%20-%20Major%20Update%5Cn%5CnFeatures%3A%5Cn-%20RGR%20(Restaurant%20General%20Review)%20checklist%20template%5Cn-%20Rich%2C%20vibrant%20color%20palette%20across%20web%20and%20mobile%5Cn-%20Luxurious%20charcoal%20sidebar%20(%230C0A09)%5Cn-%20Rich%20ruby%20red%20primary%20(%23B91C1C)%5Cn-%20Deep%20indigo%20secondary%20(%234338CA)%5Cn-%20Updated%20dashboard%20card%20gradients%5Cn-%20Start%20Audit%20button%20with%20rich%20indigo%20gradient%5Cn%5CnBug%20Fixes%3A%5Cn-%20Score%20calculation%20(capped%20at%20100%25)%5Cn-%20API%20endpoint%20routing%20fixes%5Cn-%20First-time%20login%20retry%20logic%5Cn-%20Database%20connection%20handling%5Cn%5CnUI%2FUX%3A%5Cn-%20Professional%20enterprise-grade%20design%5Cn-%20Consistent%20branding%20across%20platforms%5Cn-%20Enhanced%20visual%20hierarchy%22%7D" method="POST" type="request" pid="835,1,48" Host="audit-app-backend-2221-g9cna3ath2b4h8br.scm.centralindia-01.azurewebsites.net" User-Agent="GITHUBACTIONS_DeployWebAppToAzure_c96bb74b67676929b8fa52d523a4a19a0303a3e2ae20483f1689325f6651fabd" Authorization="Bea..." Content-Type="application/octet-stream" Cookie="ARRAffinity=33847b79e587e8df55f8922385f15b26f9612d20f5d9c93987e37e920c791d38;Path=/;HttpOnly;Secure;Domain=audit-app-backend-2221-g9cna3ath2b4h8br.scm.centralindia-01.azurewebsites.net; ARRAffinitySameSite=33847b79e587e8df55f8922385f15b26f9612d20f5d9c93987e37e920c791d38;Path=/;HttpOnly;SameSite=None;Secure;Domain=audit-app-backend-2221-g9cna3ath2b4h8br.scm.centralindia-01.azurewebsites.net" Transfer-Encoding="chunked" X-ARR-LOG-ID="a8609a93-9ee8-4da9-88aa-ac022260985c" CLIENT-IP="68.220.57.101:39968" X-SITE-DEPLOYMENT-ID="audit-app-backend-2221" WAS-DEFAULT-HOSTNAME="audit-app-backend-2221-g9cna3ath2b4h8br.scm.centralindia-01.azurewebsites.net" X-Forwarded-Proto="https" X-AppService-Proto="https" X-Forwarded-TlsVersion="1.3" X-WAWS-Unencoded-URL="/api/publish?async=true&amp;deployer=GITHUB_ONE_DEPLOY&amp;type=zip&amp;message=%7B%22type%22%3A%22deployment%22%2C%22sha%22%3A%22a452320e1d11ff70c5028d060cfb0ceaf2da885c%22%2C%22repoName%22%3A%22newthingsit%2Faudit_Checklists-app%22%2C%22actor%22%3A%22newthingsit%22%2C%22slotName%22%3A%22production%22%2C%22commitMessage%22%3A%22release%3A%20v2.0.0%20-%20Major%20Update%5Cn%5CnFeatures%3A%5Cn-%20RGR%20(Restaurant%20General%20Review)%20checklist%20template%5Cn-%20Rich%2C%20vibrant%20color%20palette%20across%20web%20and%20mobile%5Cn-%20Luxurious%20charcoal%20sidebar%20(%230C0A09)%5Cn-%20Rich%20ruby%20red%20primary%20(%23B91C1C)%5Cn-%20Deep%20indigo%20secondary%20(%234338CA)%5Cn-%20Updated%20dashboard%20card%20gradients%5Cn-%20Start%20Audit%20button%20with%20rich%20indigo%20gradient%5Cn%5CnBug%20Fixes%3A%5Cn-%20Score%20calculation%20(capped%20at%20100%25)%5Cn-%20API%20endpoint%20routing%20fixes%5Cn-%20First-time%20login%20retry%20logic%5Cn-%20Database%20connection%20handling%5Cn%5CnUI%2FUX%3A%5Cn-%20Professional%20enterprise-grade%20design%5Cn-%20Consistent%20branding%20across%20platforms%5Cn-%20Enhanced%20visual%20hierarchy%22%7D" X-Client-IP="68.220.57.101" X-Client-Port="39968" >
  <step title="OneDeploy" date="2025-12-04T15:34:59.856" >
    <step title="Starting PushDeployAsync" date="2025-12-04T15:34:59.881" /><!-- duration: 5ms -->
    <step title="Removing node_modules symlink" date="2025-12-04T15:34:59.904" >
      <step title="Writing artifact to /tmp/zipdeploy/8e47e84a-9008-4cce-9b26-e9aead83da98.zip" date="2025-12-04T15:34:59.974" >
        <step title="Writing multipart request body to /tmp/zipdeploy/8e47e84a-9008-4cce-9b26-e9aead83da98.zip" date="2025-12-04T15:34:59.979" /><!-- duration: 4ms -->
      </step><!-- duration: 4165ms -->
      <step title="Start deployment in the background" date="2025-12-04T15:35:04.171" >
        <step title="Acquiring Deployment Lock" date="2025-12-04T15:35:04.221" /><!-- duration: 3ms -->
        <step title="Acquired Deployment Lock" date="2025-12-04T15:35:04.251" /><!-- duration: 4ms -->
      </step><!-- duration: 179ms -->
    </step><!-- duration: 4450ms -->
    <step title="Outgoing response" date="2025-12-04T15:35:04.358" type="response" statusCode="202" statusText="Accepted" /><!-- duration: 4ms -->
  </step><!-- duration: 4509ms -->
