<step title="Incoming Request" date="2025-12-26T07:05:01.840" instance="582035" url="/api/deployments/latest?deployer=OneDeploy&amp;time=2025-12-26_07-03-49Z" method="GET" type="request" pid="833,1,29" Host="audit-app-backend-2221-g9cna3ath2b4h8br.scm.centralindia-01.azurewebsites.net" User-Agent="GITHUBACTIONS_DeployWebAppToAzure_c96bb74b67676929b8fa52d523a4a19a0303a3e2ae20483f1689325f6651fabd" Authorization="Bea..." Content-Type="application/json; charset=utf-8" Cookie="ARRAffinity=58203501dbaee15c4cd518c7b7697694be4cbec1031fdad6f0532854f9ed447a;Path=/;HttpOnly;Secure;Domain=audit-app-backend-2221-g9cna3ath2b4h8br.scm.centralindia-01.azurewebsites.net; ARRAffinitySameSite=58203501dbaee15c4cd518c7b7697694be4cbec1031fdad6f0532854f9ed447a;Path=/;HttpOnly;SameSite=None;Secure;Domain=audit-app-backend-2221-g9cna3ath2b4h8br.scm.centralindia-01.azurewebsites.net" Content-Length="0" X-ARR-LOG-ID="94d758c3-da32-43af-bcad-7b498747d7ac" CLIENT-IP="128.24.162.4:20506" X-SITE-DEPLOYMENT-ID="audit-app-backend-2221" WAS-DEFAULT-HOSTNAME="audit-app-backend-2221-g9cna3ath2b4h8br.scm.centralindia-01.azurewebsites.net" X-Forwarded-Proto="https" X-AppService-Proto="https" X-Forwarded-TlsVersion="1.3" X-WAWS-Unencoded-URL="/api/deployments/latest?deployer=OneDeploy&amp;time=2025-12-26_07-03-49Z" X-Client-IP="128.24.162.4" X-Client-Port="20506" >
  <step title="Cleanup Xml Logs" date="2025-12-26T07:05:01.876" >
    <step title="Cleanup Infos" date="2025-12-26T07:05:02.397" totalFiles="2089" totalCleanup="1929" /><!-- duration: 106ms -->
  </step><!-- duration: 664ms -->
  <step title="DeploymentService.GetResult" date="2025-12-26T07:05:02.590" >
    <step title="DeploymentService.GetLatestDeployment" date="2025-12-26T07:05:02.606" >
      <step title="DeploymentManager.GetResults" date="2025-12-26T07:05:02.617" /><!-- duration: 1516ms -->
    </step><!-- duration: 1545ms -->
  </step><!-- duration: 1573ms -->
  <step title="Outgoing response" date="2025-12-26T07:05:04.171" type="response" statusCode="202" statusText="Accepted" /><!-- duration: 19ms -->
</step><!-- duration: 2379ms -->
