<step title="Incoming Request" date="2025-12-19T04:21:18.087" instance="77ccbf" url="/api/publish?async=true&amp;deployer=GITHUB_ONE_DEPLOY&amp;type=zip&amp;message=%7B%22type%22%3A%22deployment%22%2C%22sha%22%3A%22fe72878677b39ef67fffe35495fe9d0b8cbb3a19%22%2C%22repoName%22%3A%22newthingsit%2Faudit_Checklists-app%22%2C%22actor%22%3A%22newthingsit%22%2C%22slotName%22%3A%22production%22%2C%22commitMessage%22%3A%22fix%3A%20Update%20progress%20bar%20to%20use%20itemsToDisplay%20for%20accurate%20progress%20calculation%22%7D" method="POST" type="request" pid="833,1,74" Host="audit-app-backend-2221-g9cna3ath2b4h8br.scm.centralindia-01.azurewebsites.net" User-Agent="GITHUBACTIONS_DeployWebAppToAzure_c96bb74b67676929b8fa52d523a4a19a0303a3e2ae20483f1689325f6651fabd" Authorization="Bea..." Content-Type="application/octet-stream" Cookie="ARRAffinity=77ccbfe25850d3e567cd1fce5a3fb621f569836ff18a1661741872db54101851;Path=/;HttpOnly;Secure;Domain=audit-app-backend-2221-g9cna3ath2b4h8br.scm.centralindia-01.azurewebsites.net; ARRAffinitySameSite=77ccbfe25850d3e567cd1fce5a3fb621f569836ff18a1661741872db54101851;Path=/;HttpOnly;SameSite=None;Secure;Domain=audit-app-backend-2221-g9cna3ath2b4h8br.scm.centralindia-01.azurewebsites.net" Transfer-Encoding="chunked" X-ARR-LOG-ID="be066499-1ca3-4421-9243-072c71042de0" CLIENT-IP="20.161.44.226:23570" X-SITE-DEPLOYMENT-ID="audit-app-backend-2221" WAS-DEFAULT-HOSTNAME="audit-app-backend-2221-g9cna3ath2b4h8br.scm.centralindia-01.azurewebsites.net" X-Forwarded-Proto="https" X-AppService-Proto="https" X-Forwarded-TlsVersion="1.3" X-WAWS-Unencoded-URL="/api/publish?async=true&amp;deployer=GITHUB_ONE_DEPLOY&amp;type=zip&amp;message=%7B%22type%22%3A%22deployment%22%2C%22sha%22%3A%22fe72878677b39ef67fffe35495fe9d0b8cbb3a19%22%2C%22repoName%22%3A%22newthingsit%2Faudit_Checklists-app%22%2C%22actor%22%3A%22newthingsit%22%2C%22slotName%22%3A%22production%22%2C%22commitMessage%22%3A%22fix%3A%20Update%20progress%20bar%20to%20use%20itemsToDisplay%20for%20accurate%20progress%20calculation%22%7D" X-Client-IP="20.161.44.226" X-Client-Port="23570" >
  <step title="OneDeploy" date="2025-12-19T04:21:18.165" >
    <step title="Starting PushDeployAsync" date="2025-12-19T04:21:18.259" /><!-- duration: 29ms -->
    <step title="Writing artifact to /tmp/zipdeploy/33b6dd65-7a42-4af3-972f-38b6c981ab7c.zip" date="2025-12-19T04:21:18.545" >
      <step title="Writing multipart request body to /tmp/zipdeploy/33b6dd65-7a42-4af3-972f-38b6c981ab7c.zip" date="2025-12-19T04:21:18.718" /><!-- duration: 185ms -->
    </step><!-- duration: 8663ms -->
    <step title="Start deployment in the background" date="2025-12-19T04:21:27.408" >
      <step title="Acquiring Deployment Lock" date="2025-12-19T04:21:28.176" /><!-- duration: 93ms -->
      <step title="Cannot Acquire Deployment Lock already held" date="2025-12-19T04:21:28.354" /><!-- duration: 56ms -->
    </step><!-- duration: 1277ms -->
    <step title="There is a deployment currently in progress. Please try again when it completes." date="2025-12-19T04:21:28.762" /><!-- duration: 27ms -->
  </step><!-- duration: 10741ms -->
  <step title="Outgoing response" date="2025-12-19T04:21:29.012" type="response" statusCode="409" statusText="Conflict" /><!-- duration: 31ms -->
</step><!-- duration: 11036ms -->
