<step title="Incoming Request" date="2025-12-04T07:28:23.754" instance="33847b" url="/api/publish?async=true&amp;deployer=GITHUB_ONE_DEPLOY&amp;type=zip&amp;message=%7B%22type%22%3A%22deployment%22%2C%22sha%22%3A%22145aa8fc84a800d09ad236b4db0dd4c7b3fcab88%22%2C%22repoName%22%3A%22newthingsit%2Faudit_Checklists-app%22%2C%22actor%22%3A%22newthingsit%22%2C%22slotName%22%3A%22production%22%2C%22commitMessage%22%3A%22feat%3A%20Add%20enhanced%20scoring%20features%20-%20scoring%20presets%2C%20weighted%20items%2C%20critical%20flags%2C%20category%20scores%22%7D" method="POST" type="request" pid="835,1,45" Host="audit-app-backend-2221-g9cna3ath2b4h8br.scm.centralindia-01.azurewebsites.net" User-Agent="GITHUBACTIONS_DeployWebAppToAzure_c96bb74b67676929b8fa52d523a4a19a0303a3e2ae20483f1689325f6651fabd" Authorization="Bea..." Content-Type="application/octet-stream" Cookie="ARRAffinity=33847b79e587e8df55f8922385f15b26f9612d20f5d9c93987e37e920c791d38;Path=/;HttpOnly;Secure;Domain=audit-app-backend-2221-g9cna3ath2b4h8br.scm.centralindia-01.azurewebsites.net; ARRAffinitySameSite=33847b79e587e8df55f8922385f15b26f9612d20f5d9c93987e37e920c791d38;Path=/;HttpOnly;SameSite=None;Secure;Domain=audit-app-backend-2221-g9cna3ath2b4h8br.scm.centralindia-01.azurewebsites.net" Transfer-Encoding="chunked" X-ARR-LOG-ID="007532e7-59b8-4fd6-b965-091c6316b110" CLIENT-IP="40.76.117.243:63488" X-SITE-DEPLOYMENT-ID="audit-app-backend-2221" WAS-DEFAULT-HOSTNAME="audit-app-backend-2221-g9cna3ath2b4h8br.scm.centralindia-01.azurewebsites.net" X-Forwarded-Proto="https" X-AppService-Proto="https" X-Forwarded-TlsVersion="1.3" X-WAWS-Unencoded-URL="/api/publish?async=true&amp;deployer=GITHUB_ONE_DEPLOY&amp;type=zip&amp;message=%7B%22type%22%3A%22deployment%22%2C%22sha%22%3A%22145aa8fc84a800d09ad236b4db0dd4c7b3fcab88%22%2C%22repoName%22%3A%22newthingsit%2Faudit_Checklists-app%22%2C%22actor%22%3A%22newthingsit%22%2C%22slotName%22%3A%22production%22%2C%22commitMessage%22%3A%22feat%3A%20Add%20enhanced%20scoring%20features%20-%20scoring%20presets%2C%20weighted%20items%2C%20critical%20flags%2C%20category%20scores%22%7D" X-Client-IP="40.76.117.243" X-Client-Port="63488" >
  <step title="OneDeploy" date="2025-12-04T07:28:23.775" >
    <step title="Starting PushDeployAsync" date="2025-12-04T07:28:23.844" /><!-- duration: 5ms -->
    <step title="Removing node_modules symlink" date="2025-12-04T07:28:23.873" >
      <step title="Writing artifact to /tmp/zipdeploy/a2a864b3-dca7-48e7-ba74-c18a269a793c.zip" date="2025-12-04T07:28:23.951" >
        <step title="Writing multipart request body to /tmp/zipdeploy/a2a864b3-dca7-48e7-ba74-c18a269a793c.zip" date="2025-12-04T07:28:23.957" /><!-- duration: 14ms -->
      </step><!-- duration: 2856ms -->
      <step title="Start deployment in the background" date="2025-12-04T07:28:26.827" >
        <step title="Acquiring Deployment Lock" date="2025-12-04T07:28:26.903" /><!-- duration: 4ms -->
        <step title="Acquired Deployment Lock" date="2025-12-04T07:28:26.938" /><!-- duration: 5ms -->
      </step><!-- duration: 244ms -->
    </step><!-- duration: 3214ms -->
    <step title="Outgoing response" date="2025-12-04T07:28:27.094" type="response" statusCode="202" statusText="Accepted" /><!-- duration: 4ms -->
  </step><!-- duration: 3327ms -->
