<step title="Incoming Request" date="2026-01-20T18:51:39.435" instance="f79140" url="/api/publish?async=true&amp;deployer=GITHUB_ONE_DEPLOY&amp;type=zip&amp;message=%7B%22type%22%3A%22deployment%22%2C%22sha%22%3A%223b14567c03a1138975701781dbbeba5ef043b724%22%2C%22repoName%22%3A%22newthingsit%2Faudit_Checklists-app%22%2C%22actor%22%3A%22newthingsit%22%2C%22slotName%22%3A%22production%22%2C%22commitMessage%22%3A%22feat%3A%20Enhanced%20CVR%20dark%20theme%20UI%20for%20web%20and%20mobile%5Cn%5Cn-%20Updated%20cvrTheme%20with%20organized%20color%20sections%20(background%2C%20text%2C%20accent%2C%20input%2C%20progress%2C%20chip%2C%20section%2C%20tab)%5Cn-%20Web%20AuditForm.js%3A%20Improved%20item%20cards%2C%20option%20buttons%2C%20progress%20bar%2C%20section%20headers%20with%20CVR%20theme%5Cn-%20Mobile%20theme.js%3A%20Synchronized%20CVR%20theme%20colors%20with%20web%20for%20consistency%5Cn-%20Added%20proper%20focus%20states%20for%20input%20fields%5Cn-%20Improved%20Required%2FCategory%20chip%20styling%5Cn-%20Enhanced%20status%20icons%20with%20CVR%20colors%22%7D" method="POST" type="request" pid="831,1,65" Host="audit-app-backend-2221-g9cna3ath2b4h8br.scm.centralindia-01.azurewebsites.net" User-Agent="GITHUBACTIONS_DeployWebAppToAzure_c96bb74b67676929b8fa52d523a4a19a0303a3e2ae20483f1689325f6651fabd" Authorization="Bea..." Content-Type="application/octet-stream" Cookie="ARRAffinity=f7914080a1e04baaab7e548dc057c38527ceb352eed71d9074f19e190f413990;Path=/;HttpOnly;Secure;Domain=audit-app-backend-2221-g9cna3ath2b4h8br.scm.centralindia-01.azurewebsites.net; ARRAffinitySameSite=f7914080a1e04baaab7e548dc057c38527ceb352eed71d9074f19e190f413990;Path=/;HttpOnly;SameSite=None;Secure;Domain=audit-app-backend-2221-g9cna3ath2b4h8br.scm.centralindia-01.azurewebsites.net" Transfer-Encoding="chunked" X-ARR-LOG-ID="dffd8182-9b87-492d-8b5d-d745ee90fa2d" CLIENT-IP="52.154.21.50:21504" X-SITE-DEPLOYMENT-ID="audit-app-backend-2221" WAS-DEFAULT-HOSTNAME="audit-app-backend-2221-g9cna3ath2b4h8br.scm.centralindia-01.azurewebsites.net" X-Forwarded-Proto="https" X-AppService-Proto="https" X-Forwarded-TlsVersion="1.3" X-WAWS-Unencoded-URL="/api/publish?async=true&amp;deployer=GITHUB_ONE_DEPLOY&amp;type=zip&amp;message=%7B%22type%22%3A%22deployment%22%2C%22sha%22%3A%223b14567c03a1138975701781dbbeba5ef043b724%22%2C%22repoName%22%3A%22newthingsit%2Faudit_Checklists-app%22%2C%22actor%22%3A%22newthingsit%22%2C%22slotName%22%3A%22production%22%2C%22commitMessage%22%3A%22feat%3A%20Enhanced%20CVR%20dark%20theme%20UI%20for%20web%20and%20mobile%5Cn%5Cn-%20Updated%20cvrTheme%20with%20organized%20color%20sections%20(background%2C%20text%2C%20accent%2C%20input%2C%20progress%2C%20chip%2C%20section%2C%20tab)%5Cn-%20Web%20AuditForm.js%3A%20Improved%20item%20cards%2C%20option%20buttons%2C%20progress%20bar%2C%20section%20headers%20with%20CVR%20theme%5Cn-%20Mobile%20theme.js%3A%20Synchronized%20CVR%20theme%20colors%20with%20web%20for%20consistency%5Cn-%20Added%20proper%20focus%20states%20for%20input%20fields%5Cn-%20Improved%20Required%2FCategory%20chip%20styling%5Cn-%20Enhanced%20status%20icons%20with%20CVR%20colors%22%7D" X-Client-IP="52.154.21.50" X-Client-Port="21504" >
  <step title="OneDeploy" date="2026-01-20T18:51:39.631" >
    <step title="Starting PushDeployAsync" date="2026-01-20T18:51:39.660" /><!-- duration: 5ms -->
    <step title="Removing node_modules symlink" date="2026-01-20T18:51:39.688" >
      <step title="Removing _del_node_modules symlink" date="2026-01-20T18:51:39.801" >
        <step title="Writing artifact to /tmp/zipdeploy/625eeef6-4976-46f7-a0b8-63d22a39e9b0.zip" date="2026-01-20T18:51:39.850" >
          <step title="Writing multipart request body to /tmp/zipdeploy/625eeef6-4976-46f7-a0b8-63d22a39e9b0.zip" date="2026-01-20T18:51:39.859" /><!-- duration: 10ms -->
        </step><!-- duration: 4034ms -->
        <step title="Start deployment in the background" date="2026-01-20T18:51:43.900" >
          <step title="Acquiring Deployment Lock" date="2026-01-20T18:51:44.045" /><!-- duration: 2ms -->
          <step title="Acquired Deployment Lock" date="2026-01-20T18:51:44.081" /><!-- duration: 4ms -->
        </step><!-- duration: 307ms -->
      </step><!-- duration: 4428ms -->
      <step title="Outgoing response" date="2026-01-20T18:51:44.240" type="response" statusCode="202" statusText="Accepted" /><!-- duration: 7ms -->
    </step><!-- duration: 4561ms -->
